streamlit_notion/__init__.py
streamlit_notion/notion_connection.py
st_notion_connection-0.0.1.dist-info/LICENSE
st_notion_connection-0.0.1.dist-info/METADATA
st_notion_connection-0.0.1.dist-info/WHEEL
st_notion_connection-0.0.1.dist-info/top_level.txt
st_notion_connection-0.0.1.dist-info/RECORD
