Metadata-Version: 2.1
Name: st-notion-connection
Version: 0.0.1
Summary: Streamlit Connection for Notion API.
Home-page: https://github.com/marks/streamlit-notion-connection
Author: Dylan Lu
Author-email: dnplus@gmail.com
License: MIT
Requires-Python: >=3.8
License-File: LICENSE
Requires-Dist: streamlit>=1.28.0
